{
  "chain_id": "equilibrium-1",
  "timestamp": "2026-07-05T00:44:37.417Z",
  "initial_supply": "100000000",
  "allocations": [
    {
      "address": "ea693e1d5d891d90d91c56fc2446c8d330a8997a",
      "amount": "40000000",
      "vesting": "none",
      "category": "community_airdrop_mining"
    },
    {
      "address": "e89ffa36b8d3d18c24f9c0aaad3328a886554d5a",
      "amount": "20000000",
      "vesting": "locked-in-pools",
      "category": "liquidity_pools"
    },
    {
      "address": "9ee64f3daeb6bb22ef2913967f9d8a8a8290d5f0",
      "amount": "15000000",
      "vesting": "2-4-year time-lock",
      "category": "ecosystem_dev_fund"
    },
    {
      "address": "d1c2c0a431299a97779cdc23837ed9ce5408aaaa",
      "amount": "5000000",
      "vesting": "none",
      "category": "founder_upfront"
    },
    {
      "address": "db4d0a79beb2001f61c671532c254ef746ab0cda",
      "amount": "5000000",
      "vesting": "4-year linear, 1-year cliff",
      "category": "founder_vested"
    },
    {
      "address": "bb18cca322f539b9750701a07e2d871fdd744566",
      "amount": "5000000",
      "vesting": "3-year linear, 1-year cliff",
      "category": "team"
    },
    {
      "address": "ab92b2d4e3591203220d707a8248a144758c2888",
      "amount": "5000000",
      "vesting": "2-3-year linear",
      "category": "advisors_early_contributors"
    }
  ],
  "initial_validators": [
    {
      "address": "6ea341f4f8d62cd427434c89d35d3fc6340a8bb1",
      "stake": "1500000",
      "name": "Equilibrium Foundation"
    },
    {
      "address": "736d0217b01cdaec6288ced8ddb8be7435f711e0",
      "stake": "1500000",
      "name": "Equilibrium Labs"
    },
    {
      "address": "cec6a4f606263f462db50d853f599b758cede73b",
      "stake": "1000000",
      "name": "Community Validator Alpha"
    },
    {
      "address": "347eae6992d4a575868c6137c707c87cb6e1a833",
      "stake": "1000000",
      "name": "Community Validator Beta"
    }
  ],
  "dex_pools": [
    {
      "pair": "EQU-WBTC",
      "reserve_a": "10000000",
      "reserve_b": "100"
    },
    {
      "pair": "EQU-USDC",
      "reserve_a": "10000000",
      "reserve_b": "10000000"
    }
  ],
  "parameters": {
    "target_block_time_ms": 15000,
    "residual_threshold": 1e-7,
    "initial_difficulty": 1000000,
    "slashing_double_sign_pct": 5,
    "slashing_downtime_pct": 1,
    "unbonding_period_blocks": 10,
    "max_validators": 100,
    "governance_quorum_pct": 33.4,
    "governance_voting_period_blocks": 10080
  }
}
